yaacs/__init__.py
yaacs/cli.py
yaacs/consts.py
yaacs/cover.py
yaacs/dispatch.py
yaacs/models.py
yaacs/py.typed
yaacs/conversion/__init__.py
yaacs/conversion/multiple.py
yaacs/conversion/single.py
yaacs/cue/__init__.py
yaacs/cue/cue.lark
yaacs/cue/cue.py
yaacs/cue/models.py
yaacs/cue/parse.py
yaacs-2.1.0.dist-info/licenses/LICENSE
yaacs-2.1.0.dist-info/METADATA
yaacs-2.1.0.dist-info/WHEEL
yaacs-2.1.0.dist-info/entry_points.txt
yaacs-2.1.0.dist-info/top_level.txt
yaacs-2.1.0.dist-info/RECORD
