Metadata-Version: 2.4
Name: yaacs
Version: 2.1.0
Summary: Convert your audiobooks to opus to save space while maintaining quality.
Author-email: Richard Garber <rg.1029384756@gmail.com>
License-Expression: GPL-2.0-only
Project-URL: Homepage, https://github.com/rgarber11/YetAnotherAudiobookConverterScript/
Project-URL: Issues, https://github.com/rgarber11/YetAnotherAudiobookConverterScript/issues
Classifier: Programming Language :: Python :: 3
Classifier: Programming Language :: Python :: 3.9
Classifier: Programming Language :: Python :: 3.10
Classifier: Programming Language :: Python :: 3.11
Classifier: Programming Language :: Python :: 3.12
Classifier: Programming Language :: Python :: 3.13
Classifier: Intended Audience :: End Users/Desktop
Classifier: Topic :: File Formats
Classifier: Topic :: Multimedia :: Sound/Audio :: Conversion
Classifier: Typing :: Typed
Requires-Python: >=3.9
License-File: LICENSE
Requires-Dist: mutagen==1.47.*
Dynamic: license-file
